django_website_tracking/__init__.py
django_website_tracking/admin.py
django_website_tracking/apps.py
django_website_tracking/cleanup.py
django_website_tracking/middleware.py
django_website_tracking/models.py
django_website_tracking-0.0.1.dist-info/LICENSE
django_website_tracking-0.0.1.dist-info/METADATA
django_website_tracking-0.0.1.dist-info/WHEEL
django_website_tracking-0.0.1.dist-info/top_level.txt
django_website_tracking-0.0.1.dist-info/RECORD
