Metadata-Version: 2.1
Name: django-website-tracking
Version: 0.0.1
Summary: Simple logging of user access to URLs in Django.
Home-page: https://gitee.com/shuhebing/django-website-tracking.git
Author: Kaixuan,Wang
Author-email: 2803268935@qq.com
License: MIT
Classifier: Environment :: Web Environment
Classifier: Framework :: Django
Classifier: Intended Audience :: Developers
Classifier: License :: OSI Approved :: MIT License
Classifier: Operating System :: OS Independent
Classifier: Programming Language :: Python :: 3
Requires-Python: >=3.6
License-File: LICENSE
Requires-Dist: Django (>=2.2)
